pic2sketch/__init__.py
pic2sketch/cli.py
pic2sketch/picture_to_sketch.py
pic2sketch/version.py
pic2sketch-0.1.0.dist-info/LICENSE
pic2sketch-0.1.0.dist-info/METADATA
pic2sketch-0.1.0.dist-info/WHEEL
pic2sketch-0.1.0.dist-info/entry_points.txt
pic2sketch-0.1.0.dist-info/top_level.txt
pic2sketch-0.1.0.dist-info/RECORD
